{
  "lastUpdated": "20 de mayo de 2026 — 20:05 UTC",
  "ticker": [
    "James Murdoch to acquire New York Magazine and Vox Media Podcast Network",
    "What’s the significance of the Russian president’s visit to China?",
    "China and Russia unite after Trump’s Beijing visit",
    "US indicts Cuba’s former leader Raul Castro: Why it matters",
    "US indicts Cuba’s Raul Castro over 1996 plane downing",
    "Sierra Leone receives first group of West African deportees from US",
    "Chris Rabb win in Pennsylvania energises Democrats’ progressive flank",
    "Russia ‘dangerously’ intercepts British spy plane over Black Sea: Ministry",
    "Meta cuts 8,000 jobs in sweeping global layoffs",
    "Controlled reopening ends Iran’s lengthy stock market shutdown",
    "Trump administration indicts Cuba’s Raul Castro over 1996 plane shootdown",
    "Trump jokes about running for Israeli prime minister",
    "Iran claims it coordinated passage of 26 vessels out of Hormuz in 24 hours",
    "At least eight killed in Israel’s air attacks on southern Lebanon",
    "Oscar-winning director calls Trump, Netanyahu and Putin ‘monsters’"
  ],
  "sections": [
    {
      "flag": "🌍",
      "label": "GEOPOLÍTICA Y CONFLICTO",
      "rows": [
        {
          "event": "Will Shohei Ohtani win the 2026 NL Cy Young Award?",
          "odds": "+452",
          "params": "Fuente: Polymarket",
          "moved": "none"
        },
        {
          "event": "Will Kevin Kiermaier win the 2026 AL Platinum Glove award?",
          "odds": "+1823",
          "params": "Fuente: Polymarket",
          "moved": "none"
        }
      ]
    },
    {
      "flag": "🏛️",
      "label": "POLÍTICA INTERNACIONAL",
      "rows": [
        {
          "event": "Will Renan Santos finish in second place in the first round of the 2026 Brazilian presidential election?",
          "odds": "+920",
          "params": "Fuente: Polymarket",
          "moved": "none"
        },
        {
          "event": "Will Jean Castex be on the ballot for the 2027 French presidential election?",
          "odds": "+900",
          "params": "Fuente: Polymarket",
          "moved": "none"
        },
        {
          "event": "Will the Republicans win the 2028 US Presidential Election?",
          "odds": "+163",
          "params": "Fuente: Polymarket",
          "moved": "none"
        },
        {
          "event": "Will Marco Rubio win the 2028 US Presidential Election?",
          "odds": "+657",
          "params": "Fuente: Polymarket",
          "moved": "none"
        },
        {
          "event": "Will Prabowo Subianto cease to be President of Indonesia by May 31, 2026?",
          "odds": "+149",
          "params": "Fuente: Polymarket",
          "moved": "none"
        },
        {
          "event": "Will J.D. Vance be the 2028 Republican Vice-Presidential nominee?",
          "odds": "+900",
          "params": "Fuente: Polymarket",
          "moved": "none"
        },
        {
          "event": "Will the Republican Party hold exactly 50 Senate seats after the 2026 midterm elections?",
          "odds": "+566",
          "params": "Fuente: Polymarket",
          "moved": "none"
        }
      ]
    },
    {
      "flag": "🌐",
      "label": "ESCENARIOS GLOBALES",
      "rows": [
        {
          "event": "World Championships: Slovakia vs. Canada",
          "odds": "+614",
          "params": "Fuente: Polymarket",
          "moved": "none"
        },
        {
          "event": "World Championships: Czechia vs. Norway",
          "odds": "-455",
          "params": "Fuente: Polymarket",
          "moved": "none"
        },
        {
          "event": "Abstract FDV above $200M one day after launch?",
          "odds": "-316",
          "params": "Fuente: Polymarket",
          "moved": "none"
        },
        {
          "event": "Will the Reserve Bank of Australia increase the target for the cash rate after the June Meeting?",
          "odds": "+354",
          "params": "Fuente: Polymarket",
          "moved": "none"
        },
        {
          "event": "Will Sofia host Eurovision 2027?",
          "odds": "-733",
          "params": "Fuente: Polymarket",
          "moved": "none"
        },
        {
          "event": "Will the Democratic Party win the CA-24 House seat?",
          "odds": "-1328",
          "params": "Fuente: Polymarket",
          "moved": "none"
        },
        {
          "event": "Will the highest temperature in Beijing be 24°C on May 21?",
          "odds": "+1566",
          "params": "Fuente: Polymarket",
          "moved": "none"
        },
        {
          "event": "Will Monero hit $1000 in 2026?",
          "odds": "+809",
          "params": "Fuente: Polymarket",
          "moved": "none"
        }
      ]
    }
  ]
}