{
  "lastUpdated": "02 de marzo de 2026 — 17:08 CDMX",
  "ticker": [
    "Tensión política en Ucrania aumenta",
    "Mercado financiero experimenta fluctuaciones",
    "Nuevas medidas de seguridad en la frontera de Estados Unidos",
    "Desarrollo de tecnología de inteligencia artificial avanza rápidamente"
  ],
  "sections": [
    {
      "flag": "geopolitica",
      "label": "Geopolítica",
      "rows": [
        {
          "event": "Conflicto en Medio Oriente",
          "odds": 0.35,
          "moved": "up",
          "params": {
            "region": "Medio Oriente",
            "actores": [
              "Estados Unidos",
              "Irán"
            ]
          }
        },
        {
          "event": "Tensión en la península de Corea",
          "odds": 0.42,
          "moved": "none",
          "params": {
            "region": "Asia",
            "actores": [
              "Corea del Norte",
              "Corea del Sur",
              "Estados Unidos"
            ]
          }
        }
      ]
    },
    {
      "flag": "economia",
      "label": "Economía",
      "rows": [
        {
          "event": "Recesión económica global",
          "odds": 0.28,
          "moved": "down",
          "params": {
            "indicadores": [
              "PIB",
              "inflación"
            ],
            "regiones": [
              "Europa",
              "América del Norte"
            ]
          }
        },
        {
          "event": "Crisis financiera en China",
          "odds": 0.18,
          "moved": "up",
          "params": {
            "sector": "finanzas",
            "actores": [
              "Gobierno chino",
              "inversores extranjeros"
            ]
          }
        }
      ]
    }
  ]
}