{
  "lastUpdated": "04 de mayo de 2026 — 19:20 UTC",
  "ticker": [
    "Gangland wars killing dozens of bystanders, report Swedish police",
    "Iran-US clash over alleged warship attack in Strait of Hormuz",
    "Zambia delaying US deals over minerals and data demands",
    "Tackling methane emissions key for climate change and energy security: IEA",
    "Car ploughs into pedestrians in central Leipzig, Germany",
    "Car-ramming incident kills at least two people in Germany",
    "US Supreme Court temporarily lifts ban on abortion pill mail delivery",
    "Nepal lodges protest against India over long-running border dispute",
    "Captain warns ‘no ship will be a hero’ by risking Hormuz transit",
    "Would you bet on the next disaster? The rise of prediction markets",
    "GameStop targets eBay with unsolicited $56bn acquisition offer",
    "Lebanon Latest",
    "US releases Touska container ship crew: Why it matters",
    "US official says China is ‘funding’ Iran, urges Beijing to help open Hormuz",
    "UAE reports missile and drone strikes incoming from Iran"
  ],
  "sections": [
    {
      "flag": "🌍",
      "label": "GEOPOLÍTICA Y CONFLICTO",
      "rows": [
        {
          "event": "Will Jacob deGrom win the 2026 AL Cy Young Award?",
          "odds": "+3025",
          "params": "Fuente: Polymarket",
          "moved": "none"
        },
        {
          "event": "NATO x Russia military clash by December 31, 2026?",
          "odds": "+400",
          "params": "Fuente: Polymarket",
          "moved": "none"
        },
        {
          "event": "Will Capitão Wagner win the 2026 Ceará gubernatorial election?",
          "odds": "+1251",
          "params": "Fuente: Polymarket",
          "moved": "none"
        },
        {
          "event": "US x Cuba military clash in 2026?",
          "odds": "+122",
          "params": "Fuente: Polymarket",
          "moved": "none"
        },
        {
          "event": "Will Donald Trump visit China on May 13, 2026?",
          "odds": "-122",
          "params": "Fuente: Polymarket",
          "moved": "none"
        },
        {
          "event": "Will the Communist Party of the Russian Federation (KPRF) win the third-most seats in the next Russian parliamentary election?",
          "odds": "+400",
          "params": "Fuente: Polymarket",
          "moved": "none"
        },
        {
          "event": "Will US withdraw from NATO before 2027?",
          "odds": "+1049",
          "params": "Fuente: Polymarket",
          "moved": "none"
        }
      ]
    },
    {
      "flag": "💰",
      "label": "ECONOMÍA Y RECURSOS",
      "rows": [
        {
          "event": "Will US crude oil reserves fall to 325M by June 5?",
          "odds": "+257",
          "params": "Fuente: Polymarket",
          "moved": "none"
        },
        {
          "event": "Will S&P 500 (SPX) hit $8,200 (HIGH) in December?",
          "odds": "+426",
          "params": "Fuente: Polymarket",
          "moved": "none"
        },
        {
          "event": "Fed rate hike in 2026?",
          "odds": "+334",
          "params": "Fuente: Polymarket",
          "moved": "none"
        },
        {
          "event": "Fed rate cut by December 2026 meeting?",
          "odds": "+177",
          "params": "Fuente: Polymarket",
          "moved": "none"
        },
        {
          "event": "Will the Fed’s lower bound reach 0.5% or lower before 2027?",
          "odds": "+1119",
          "params": "Fuente: Polymarket",
          "moved": "none"
        },
        {
          "event": "Will S&P 500 (SPY) hit (HIGH) $780 in May?",
          "odds": "+1685",
          "params": "Fuente: Polymarket",
          "moved": "none"
        },
        {
          "event": "Will OPEC crude oil production be above 20 million barrels per day in May?",
          "odds": "+1011",
          "params": "Fuente: Polymarket",
          "moved": "none"
        }
      ]
    },
    {
      "flag": "🏛️",
      "label": "POLÍTICA INTERNACIONAL",
      "rows": [
        {
          "event": "Will Iván Cepeda Castro win the first round of the 2026 Colombian presidential election by 20%+?",
          "odds": "+669",
          "params": "Fuente: Polymarket",
          "moved": "none"
        },
        {
          "event": "Will Paloma Valencia win the 2026 Colombian presidential election?",
          "odds": "+269",
          "params": "Fuente: Polymarket",
          "moved": "none"
        },
        {
          "event": "Will Partido Social Democrático (PSD) win the most seats in the next Brazilian Senate election?",
          "odds": "+2400",
          "params": "Fuente: Polymarket",
          "moved": "none"
        },
        {
          "event": "Will Renan Santos finish in second place in the first round of the 2026 Brazilian presidential election?",
          "odds": "+1983",
          "params": "Fuente: Polymarket",
          "moved": "none"
        },
        {
          "event": "Will John Thune be the next Senate Majority Leader?",
          "odds": "+284",
          "params": "Fuente: Polymarket",
          "moved": "none"
        },
        {
          "event": "Will Mark Lynch be the Republican nominee for Senate in South Carolina?",
          "odds": "+941",
          "params": "Fuente: Polymarket",
          "moved": "none"
        },
        {
          "event": "Will Mike Kennealy win the 2026 Massachusetts Governor Republican primary election?",
          "odds": "+669",
          "params": "Fuente: Polymarket",
          "moved": "none"
        }
      ]
    },
    {
      "flag": "🌐",
      "label": "ESCENARIOS GLOBALES",
      "rows": [
        {
          "event": "Will ForecastEx self-certify sports event contracts by June 30, 2026?",
          "odds": "+257",
          "params": "Fuente: Polymarket",
          "moved": "none"
        },
        {
          "event": "Will the highest temperature in Beijing be 26°C on May 6?",
          "odds": "+354",
          "params": "Fuente: Polymarket",
          "moved": "none"
        },
        {
          "event": "Will Xi Jinping purge Wang Huning in 2026?",
          "odds": "+2841",
          "params": "Fuente: Polymarket",
          "moved": "none"
        },
        {
          "event": "Will Oliver Adams Larkin be the Democratic Nominee for FL-23?",
          "odds": "+127",
          "params": "Fuente: Polymarket",
          "moved": "none"
        },
        {
          "event": "Will Amanda Anisimova be the 2026 Women’s Wimbledon Winner?",
          "odds": "+3025",
          "params": "Fuente: Polymarket",
          "moved": "none"
        },
        {
          "event": "Will White House post 140-159 posts from May 1 to May 8, 2026?",
          "odds": "+127",
          "params": "Fuente: Polymarket",
          "moved": "none"
        },
        {
          "event": "LoL: Team WE vs Invictus Gaming (BO3) - LPL Group Ascend",
          "odds": "+488",
          "params": "Fuente: Polymarket",
          "moved": "none"
        },
        {
          "event": "Will IONQ (IONQ) beat quarterly earnings?",
          "odds": "-762",
          "params": "Fuente: Polymarket",
          "moved": "none"
        }
      ]
    }
  ]
}