{
  "lastUpdated": "19 de junio de 2026 — 14:49 UTC",
  "ticker": [
    "As Lebanon tests US-Iran deal, Trump must rein in Netanyahu, analysts say",
    "Cuba approves major economic reforms amid US pressure",
    "Israel slams EU’s Kallas for ‘apartheid’ comment: Are ties unravelling?",
    "Sudanese journalist denied UK visa to collect prestigious award",
    "British lawyers’ body suspends ICC Prosecutor Khan over misconduct claim",
    "Chile’s Palestinians push back against Israel policy shift",
    "Search continues for kidnapped Mexican journalist Roxana Guzman",
    "Starmer’s future hangs in balance after Burnham’s Makerfield election win",
    "Afghanistan strikes targets in Pakistan, raising cross-border tension",
    "Could the HPV vaccine eliminate cervical cancer deaths?",
    "Trump hints at new approach to North Korea’s nuclear programme",
    "World Cup: Will Pulisic play against Australia and can USMNT qualify?",
    "Arsenal to begin Premier League title defence against promoted Coventry",
    "Brazil vs Haiti: World Cup – Prediction, how to watch and will Neymar play?",
    "Can US-Iran peace ‘deal’ survive Israeli bombing of Lebanon?"
  ],
  "sections": [
    {
      "flag": "🌍",
      "label": "GEOPOLÍTICA Y CONFLICTO",
      "rows": [
        {
          "event": "Namibia T20 Tri-Series: Namibia vs Hong Kong, China - Who wins the toss?",
          "odds": "-1899",
          "params": "Fuente: Polymarket",
          "moved": "none"
        }
      ]
    },
    {
      "flag": "💰",
      "label": "ECONOMÍA Y RECURSOS",
      "rows": [
        {
          "event": "Will the US federal government take a stake in Freeport-McMoRan Inc.?",
          "odds": "+488",
          "params": "Fuente: Polymarket",
          "moved": "none"
        }
      ]
    },
    {
      "flag": "🏛️",
      "label": "POLÍTICA INTERNACIONAL",
      "rows": [
        {
          "event": "Will Ulf Kristersson be the next Prime Minister of Sweden?",
          "odds": "+316",
          "params": "Fuente: Polymarket",
          "moved": "none"
        },
        {
          "event": "Will Nithya Raman win the 2026 Los Angeles mayoral election?",
          "odds": "+165",
          "params": "Fuente: Polymarket",
          "moved": "none"
        },
        {
          "event": "Will Pete Buttigieg announce a Presidential run before 2027?",
          "odds": "+614",
          "params": "Fuente: Polymarket",
          "moved": "none"
        },
        {
          "event": "Will New Zealand First Party win the third-most seats in the New Zealand House of Representatives in the 2026 New Zealand legislative election?",
          "odds": "-138",
          "params": "Fuente: Polymarket",
          "moved": "none"
        }
      ]
    },
    {
      "flag": "🌐",
      "label": "ESCENARIOS GLOBALES",
      "rows": [
        {
          "event": "Will \"Disclosure Day\" 2nd Weekend Box Office be between 22m and 24m?",
          "odds": "+1899",
          "params": "Fuente: Polymarket",
          "moved": "none"
        },
        {
          "event": "Will Puffpaw launch a token by September 30, 2026?",
          "odds": "+149",
          "params": "Fuente: Polymarket",
          "moved": "none"
        },
        {
          "event": "Will Google have a #1 AI model by December 31, 2026?",
          "odds": "+127",
          "params": "Fuente: Polymarket",
          "moved": "none"
        },
        {
          "event": "Will the highest temperature in Mexico City be 24°C on June 20?",
          "odds": "+194",
          "params": "Fuente: Polymarket",
          "moved": "none"
        },
        {
          "event": "Will the highest temperature in Wellington be 17°C on June 21?",
          "odds": "+127",
          "params": "Fuente: Polymarket",
          "moved": "none"
        },
        {
          "event": "Will Portugal win on 2026-06-27?",
          "odds": "+112",
          "params": "Fuente: Polymarket",
          "moved": "none"
        },
        {
          "event": "Will Trump say \"Too Big To Rig\" this week?",
          "odds": "+1566",
          "params": "Fuente: Polymarket",
          "moved": "none"
        },
        {
          "event": "Will the highest temperature in Milan be 34°C on June 21?",
          "odds": "+376",
          "params": "Fuente: Polymarket",
          "moved": "none"
        }
      ]
    }
  ]
}